nonebot_plugin_who_at_me/__init__.py
nonebot_plugin_who_at_me/config.py
nonebot_plugin_who_at_me/data_source.py
nonebot_plugin_who_at_me/database.py
nonebot_plugin_who_at_me/rule.py
nonebot_plugin_who_at_me/utils.py
nonebot_plugin_who_at_me-0.3.3.dist-info/LICENSE
nonebot_plugin_who_at_me-0.3.3.dist-info/WHEEL
nonebot_plugin_who_at_me-0.3.3.dist-info/METADATA
nonebot_plugin_who_at_me-0.3.3.dist-info/RECORD
