Metadata-Version: 2.1
Name: nonebot-plugin-who-at-me
Version: 0.3.3
Summary: Find who on earth has ated you
Home-page: https://github.com/SEAFHMC/nonebot-plugin-who-at-me
License: MIT
Author: SEAFHMC
Author-email: soku_ritsuki@outlook.com
Requires-Python: >=3.8,<4.0
Classifier: License :: OSI Approved :: MIT License
Classifier: Programming Language :: Python :: 3
Classifier: Programming Language :: Python :: 3.10
Classifier: Programming Language :: Python :: 3.8
Classifier: Programming Language :: Python :: 3.9
Requires-Dist: black (>=22.8.0,<23.0.0)
Requires-Dist: nonebot-adapter-onebot (>=2.1.1,<3.0.0)
Requires-Dist: nonebot2 (>=2.0.0-beta.4,<3.0.0)
Requires-Dist: peewee (>=3.14.4)
Requires-Dist: pydantic (==2.10.6)
Project-URL: Documentation, https://github.com/SEAFHMC/nonebot-plugin-who-at-me/blob/main/README.md
Project-URL: Repository, https://github.com/SEAFHMC/nonebot-plugin-who-at-me
